nbbrowserpdf/__init__.py
nbbrowserpdf/_version.py
nbbrowserpdf/convert.py
nbbrowserpdf/install.py
nbbrowserpdf/exporters/__init__.py
nbbrowserpdf/exporters/base.py
nbbrowserpdf/exporters/pdf.py
nbbrowserpdf/exporters/pdf_capture.py
nbbrowserpdf/static/nbbrowserpdf/index.js
nbbrowserpdf/templates/browserpdf-polyfills.tpl
nbbrowserpdf/templates/browserpdf.tpl
nbbrowserpdf-0.2.0.dist-info/DESCRIPTION.rst
nbbrowserpdf-0.2.0.dist-info/METADATA
nbbrowserpdf-0.2.0.dist-info/RECORD
nbbrowserpdf-0.2.0.dist-info/WHEEL
nbbrowserpdf-0.2.0.dist-info/metadata.json
nbbrowserpdf-0.2.0.dist-info/top_level.txt
