Metadata-Version: 2.0
Name: nbbrowserpdf
Version: 0.2.0
Summary: LaTeX-free PDF generation from Jupyter Notebooks
Home-page: https://github.com/Anaconda-Server/nbbrowserpdf
Author: Nicholas Bollweg
Author-email: nbollweg@continuum.io
License: BSD-3-Clause
Keywords: ipython jupyter pdf qt webkit
Platform: UNKNOWN
Classifier: Development Status :: 4 - Beta
Classifier: Framework :: IPython
Classifier: Programming Language :: Python
Classifier: Programming Language :: Python :: 2
Classifier: Programming Language :: Python :: 3
Classifier: License :: OSI Approved :: BSD License
Requires-Dist: ghost.py
Requires-Dist: pypdf2
